VIOKiS/__init__.py
VIOKiS/simple_selects.py
VIOKiS/test_public.py
VIOKiS-0.0.1.dist-info/METADATA
VIOKiS-0.0.1.dist-info/WHEEL
VIOKiS-0.0.1.dist-info/top_level.txt
VIOKiS-0.0.1.dist-info/RECORD
