Metadata-Version: 2.1
Name: VIOKiS
Version: 0.0.1
Summary: Simple_selects
Home-page: UNKNOWN
Author: Violetta Kishkurno
License: UNKNOWN
Keywords: python
Platform: UNKNOWN
Classifier: Development Status :: 3 - Alpha
Classifier: Operating System :: Microsoft :: Windows
Requires-Dist: pypika
